osm_to_sandbox/__init__.py
osm_to_sandbox/osm_to_sandbox.py
osm_to_sandbox-1.2.dist-info/LICENSE.md
osm_to_sandbox-1.2.dist-info/METADATA
osm_to_sandbox-1.2.dist-info/WHEEL
osm_to_sandbox-1.2.dist-info/entry_points.txt
osm_to_sandbox-1.2.dist-info/top_level.txt
osm_to_sandbox-1.2.dist-info/RECORD
