Metadata-Version: 2.1
Name: osm_to_sandbox
Version: 1.2
Summary: Copy data from OpenStreetMap to its Mapping Sandbox
Home-page: https://github.com/Zverik/osm_to_sandbox
Author: Ilya Zverev
Author-email: ilya@zverev.info
License: ISC License
Keywords: osm,openstreetmap,sandbox,copy
Classifier: Development Status :: 5 - Production/Stable
Classifier: Environment :: Console
Classifier: Intended Audience :: Information Technology
Classifier: Intended Audience :: Customer Service
Classifier: Operating System :: OS Independent
Classifier: License :: OSI Approved :: ISC License (ISCL)
Classifier: Programming Language :: Python :: 3 :: Only
Requires-Python: >=3.5
License-File: LICENSE.md
Requires-Dist: requests
Requires-Dist: lxml
Requires-Dist: cli-oauth2
